ngstoolkits/Fasta.py
ngstoolkits/__init__.py
ngstoolkits/class_bam.py
ngstoolkits/config.py
ngstoolkits/cpra.py
ngstoolkits/cytogenetic_bands.py
ngstoolkits/loadData.py
ngstoolkits/sequence.py
ngstoolkits/units.py
ngstoolkits/anno/__init__.py
plot/dag.py
ngstoolkits-1.0.1rc1.dist-info/LICENSE.txt
ngstoolkits-1.0.1rc1.dist-info/METADATA
ngstoolkits-1.0.1rc1.dist-info/WHEEL
ngstoolkits-1.0.1rc1.dist-info/top_level.txt
ngstoolkits-1.0.1rc1.dist-info/RECORD
