Metadata-Version: 2.1
Name: ngstoolkits
Version: 1.0.1rc1
Summary: ngstoolkits
Home-page: https://github.com/Ben-unbelieveable/package_ngstoolkits/
Author: Liubo
Author-email: 614347533@qq.com
License: MIT
Project-URL: pypi, https://pypi.org/project/ngstoolkits/
Project-URL: Changelog, https://github.com/Ben-unbelieveable/package_ngstoolkits/blob/master/CHANGELOG.md
Project-URL: Tracker, https://github.com/Ben-unbelieveable/package_ngstoolkits/issues
Platform: any
Classifier: Development Status :: 4 - Beta
Classifier: Programming Language :: Python
Requires-Python: >=3.8
License-File: LICENSE.txt
Requires-Dist: pysam >=0.16.0
Requires-Dist: pyyaml
Requires-Dist: importlib-metadata ; python_version < "3.8"
Provides-Extra: testing
Requires-Dist: setuptools ; extra == 'testing'
Requires-Dist: pytest ; extra == 'testing'
Requires-Dist: pytest-cov ; extra == 'testing'
